{
  "olc_db": {
    "permissions": {
      "ID1": {
        "active": "true",
        "created": "2019/03/12",
        "desciption": "PUBLIC"
      },
      "ID2": {
        "active": "true",
        "created": "2019/03/12",
        "desciption": "COMERCIAL"
      },
      "ID99": {
        "active": "true",
        "created": "2019/03/12",
        "desciption": "ADMIN"
      }
    },
    "users": {
      "0TiIWbsyXYXNPJeQMlAZ7dWiJeW2": {
        "active": true,
        "cep": "sdfsdf",
        "created": "Mon, 19 Oct 2020 21:08:30 GMT",
        "email": "vanelli@teste.com",
        "name": "Vanelli vanelli",
        "permission_id": "ID1",
        "photoUrl": "",
        "uid": "0TiIWbsyXYXNPJeQMlAZ7dWiJeW2",
        "ultimoLogin": "Tue, 27 Oct 2020 18:46:40 GMT"
      },
      "rUBfZryn0qPBvoRMHiHJyIAvUeq1": {
        "active": true,
        "cep": "79995444",
        "created": "Thu, 29 Oct 2020 19:38:33 GMT",
        "email": "sapukams@gmail.com",
        "name": "Sapukams",
        "permission_id": "ID1",
        "photoUrl": "",
        "uid": "rUBfZryn0qPBvoRMHiHJyIAvUeq1",
        "ultimoLogin": "Thu, 29 Oct 2020 19:38:33 GMT"
      }
    },
    "imoveis_venda": {
      "ID5528": {
        "active": true,
        "created": "25/02/2020",
        "categoria": "casa",
        "valor": 250000,
        "titulo": "Casa a venda da rua no nada",
        "quartos": 3,
        "garagem": 1,
        "area": 100,
        "banheiros": 2,
        "fotos": "wqewqewqscsdch54",
        "estado": "MS",
        "cidade": "campo grande",
        "bairro": "morumbi",
        "cep": "79051510",
        "condominio_active": true,
        "condominio_valor": 240,
        "piscina_active": true,
        "academia_active": true,
        "portaria_active": true,
        "vendedor": "0TiIWbsyXYXNPJeQMlAZ7dWiJeW2"
      },
      "ID5529": {
        "active": true,
        "created": "17/10/2020",
        "categoria": "apartamento",
        "valor": 300000,
        "titulo": "Apartamento novo com sacada",
        "quartos": 3,
        "garagem": 1,
        "area": 100,
        "banheiros": 2,
        "fotos": "wqewqewqscsdch54",
        "estado": "MS",
        "cidade": "campo grande",
        "bairro": "morumbi",
        "cep": "79051510",
        "condominio_active": true,
        "condominio_valor": 140,
        "piscina_active": true,
        "academia_active": true,
        "portaria_active": true,
        "vendedor": "0TiIWbsyXYXNPJeQMlAZ7dWiJeW2"
      },
      "ID5530": {
        "active": true,
        "created": "01/05/2017",
        "categoria": "terreno",
        "valor": 100000,
        "titulo": "Terreno perto da escola",
        "quartos": 3,
        "garagem": 1,
        "area": 100,
        "banheiros": 2,
        "fotos": "wqewqewqscsdch54",
        "estado": "SP",
        "cidade": "sao paulo",
        "bairro": "morumbi",
        "cep": "79051510",
        "condominio_active": false,
        "condominio_valor": null,
        "piscina_active": false,
        "academia_active": false,
        "portaria_active": false,
        "vendedor": "0TiIWbsyXYXNPJeQMlAZ7dWiJeW2"
      }
    }
  }
}